<?xml version="1.0" encoding="utf-8"?>
<BanditInvasion>
  <Bandit name="Bandit1" count="1" probability="0.5"/>
  <Bandit name="Bandit2" count="1" probability="0.5"/>
  <Bandit name="Bandit3" count="1" probability="0.5"/>
  <Bandit name="Bandit4" count="1" probability="0.5"/>
  <Bandit name="Bandit5" count="1" probability="0.5"/>
  <Bandit name="Bandit6" count="1" probability="0.5"/>
  <Bandit name="Bandit8" count="1" probability="0.5"/>
  <Bandit name="Bandit9" count="1" probability="0.15"/>
  <Bandit name="Bandit10" count="1" probability="0.20"/>
  <Bandit name="Bandit13" count="1" probability="0.15"/>
  <Bandit name="Bandit14" count="1" probability="0.10"/>
  <Bandit name="Bandit15" count="1" probability="0.10"/>
  <Bandit name="Bandit16" count="1" probability="0.08"/>
  <Bandit name="Bandit17" count="1" probability="0.05"/>
</BanditInvasion>
